ctmu/__init__.py
ctmu/backup_utils.py
ctmu/cache_manager.py
ctmu/cli.py
ctmu/core.py
ctmu/dev_utils.py
ctmu/favicon_fetcher.py
ctmu/gpg_utils.py
ctmu/image_processor.py
ctmu/math_utils.py
ctmu/media_utils.py
ctmu/monitor_utils.py
ctmu/qr_generator.py
ctmu/storage.py
ctmu/stylers.py
ctmu/terminal_factory.py
ctmu/text_utils.py
ctmu/time_utils.py
ctmu/utils.py
ctmu/validators.py
ctmu/web_utils.py
ctmu-2.1.0.dist-info/licenses/LICENSE
ctmu-2.1.0.dist-info/METADATA
ctmu-2.1.0.dist-info/WHEEL
ctmu-2.1.0.dist-info/entry_points.txt
ctmu-2.1.0.dist-info/top_level.txt
ctmu-2.1.0.dist-info/RECORD
