Metadata-Version: 2.4
Name: ctmu
Version: 2.1.0
Summary: Swiss Army Knife CLI tool for macOS - QR codes, hashing, networking, file ops, and more
Home-page: https://github.com/JohnThre/CTMU-for-macOS
Author: CTMU Development Team
License: GPL-3.0
Project-URL: Bug Tracker, https://github.com/JohnThre/CTMU-for-macOS/issues
Project-URL: Documentation, https://github.com/JohnThre/CTMU-for-macOS#readme
Project-URL: Source Code, https://github.com/JohnThre/CTMU-for-macOS
Classifier: License :: OSI Approved :: GNU General Public License v3 (GPLv3)
Classifier: Programming Language :: Python :: 3
Classifier: Programming Language :: Python :: 3.8
Classifier: Programming Language :: Python :: 3.9
Classifier: Programming Language :: Python :: 3.10
Classifier: Programming Language :: Python :: 3.11
Classifier: Programming Language :: Python :: 3.12
Classifier: Operating System :: MacOS
Classifier: Environment :: Console
Classifier: Topic :: Utilities
Classifier: Topic :: System :: Systems Administration
Requires-Python: >=3.8
License-File: LICENSE
Requires-Dist: qrcode[pil]>=7.4.2
Requires-Dist: Pillow>=10.0.0
Requires-Dist: requests>=2.31.0
Requires-Dist: click>=8.1.0
Dynamic: author
Dynamic: classifier
Dynamic: description
Dynamic: description-content-type
Dynamic: home-page
Dynamic: license
Dynamic: license-file
Dynamic: project-url
Dynamic: requires-dist
Dynamic: requires-python
Dynamic: summary
